README.md
setup.py
edict/__init__.py
edict/dig.py
edict/edict.py
edict.egg-info/PKG-INFO
edict.egg-info/SOURCES.txt
edict.egg-info/dependency_links.txt
edict.egg-info/top_level.txt