Metadata-Version: 1.1
Name: edict
Version: 0.43
Summary: handle dict,nested Dict,APIs
Home-page: https://github.com/ihgazni2/edict
Author: dapeli
Author-email: terryinzaghi@163.com
License: MIT
Platform: UNKNOWN
Classifier: Environment :: Console
Classifier: Environment :: Web Environment
Classifier: Intended Audience :: End Users/Desktop
Classifier: Intended Audience :: Developers
Classifier: Intended Audience :: System Administrators
Classifier: Programming Language :: Python
